psptrace/__init__.py
psptrace/__main__.py
psptrace/psptrace.py
psptrace/winbond_instructions.py
psptrace-0.11.dist-info/METADATA
psptrace-0.11.dist-info/WHEEL
psptrace-0.11.dist-info/entry_points.txt
psptrace-0.11.dist-info/licenses/LICENSE
psptrace-0.11.dist-info/RECORD
