Metadata-Version: 2.4
Name: psptrace
Version: 0.11
Summary: PSPTrace can correlate an SPI capture of an AMD boot procedure to the PSP firmware components
Author-email: Christian Werling <cwerling@posteo.de>
License-File: LICENSE
Requires-Python: >=3.8
Requires-Dist: prettytable
Requires-Dist: psptool>=3.0
